enderturing/__init__.py
enderturing/api/__init__.py
enderturing/api/agent.py
enderturing/api/api_utils.py
enderturing/api/asr.py
enderturing/api/connectors.py
enderturing/api/filters.py
enderturing/api/hashtags.py
enderturing/api/playlists.py
enderturing/api/raw.py
enderturing/api/reports.py
enderturing/api/schemas/__init__.py
enderturing/api/schemas/search_response.py
enderturing/api/scorecards.py
enderturing/api/services.py
enderturing/api/sessions.py
enderturing/api/system.py
enderturing/api/tags.py
enderturing/api/trainings.py
enderturing/api/triggers.py
enderturing/api/users.py
enderturing/config/__init__.py
enderturing/config/asr_config.py
enderturing/config/config.py
enderturing/config/config_utils.py
enderturing/enderturing.py
enderturing/ffmpeg_helper.py
enderturing/http_client.py
enderturing/recognition_stream.py
enderturing/speech_recognizer.py
enderturing-0.10.1.dist-info/LICENSE
enderturing-0.10.1.dist-info/METADATA
enderturing-0.10.1.dist-info/WHEEL
enderturing-0.10.1.dist-info/RECORD
