Metadata-Version: 2.1
Name: enderturing
Version: 0.10.1
Summary: Python SDK for EnderTuring speech toolkit
Home-page: https://enderturing.com/
License: MIT
Keywords: ASR,speech,enderturing
Author: EnderTuring
Author-email: info@enderturing.com
Requires-Python: >=3.9
Classifier: Intended Audience :: Developers
Classifier: Intended Audience :: Telecommunications Industry
Classifier: License :: OSI Approved :: MIT License
Classifier: Programming Language :: Python :: 3
Classifier: Programming Language :: Python :: 3.9
Classifier: Programming Language :: Python :: 3.10
Classifier: Programming Language :: Python :: 3.11
Classifier: Programming Language :: Python :: 3.12
Classifier: Topic :: Multimedia :: Sound/Audio
Classifier: Topic :: Multimedia :: Sound/Audio :: Analysis
Classifier: Topic :: Multimedia :: Sound/Audio :: Sound Synthesis
Classifier: Topic :: Multimedia :: Sound/Audio :: Speech
Requires-Dist: pydantic (>=2.0.0,<3.0.0)
Requires-Dist: requests (>=2.28.0,<3.0.0)
Requires-Dist: websockets (>=10.0,<=12.0)
Project-URL: Repository, https://github.com/EnderTuringHQ/enderturing-sdk-python
